{
  "users": [
    {
      "id": 0,
      "isActive": true,
      "balance": "$3,633.53",
      "picture": "http://placehold.it/128x128",
      "age": "22",
      "accessLevel": "guest",
      "firstName": "Richardson",
      "lastName": "Gilbert",
      "company": "TELEPARK",
      "email": "richardson.gilbert@telepark.co.uk",
      "phone": "+7 (809) 441-3603",
      "address": "325 Marconi Place, Cobbtown, Rhode Island, 9889",
      "about": "Lorem aute veniam eu adipisicing culpa labore proident culpa laborum anim pariatur duis commodo ut. Proident officia eiusmod ut aliqua aliqua ipsum pariatur amet est Lorem. Et mollit enim amet proident nostrud enim reprehenderit sit et laboris deserunt adipisicing. Exercitation adipisicing fugiat laboris consectetur sit quis consequat magna veniam sit. Dolor elit reprehenderit excepteur excepteur adipisicing qui enim. Nisi ullamco amet eu ullamco.",
      "registered": "29.01.2018"
    },
    {
      "id": 1,
      "isActive": false,
      "balance": "$2,217.49",
      "picture": "http://placehold.it/128x128",
      "age": 32,
      "accessLevel": "guest",
      "firstName": "Mariana",
      "lastName": "Gilliam",
      "company": "KIDSTOCK",
      "email": "mariana.gilliam@kidstock.us",
      "phone": "+7 (859) 437-3654",
      "address": "155 Highland Avenue, Bayview, Virgin Islands, 310",
      "about": "Ex amet commodo sunt esse eu veniam nisi sunt ad consectetur sit dolore. Mollit sint non aute nisi ad. Proident exercitation incididunt pariatur elit anim ex proident duis. Proident elit veniam non ut ipsum culpa do. Eu aliqua quis incididunt commodo enim non anim ipsum ex labore minim.",
      "registered": "03.05.2014"
    },
    {
      "id": 2,
      "isActive": false,
      "balance": "$3,202.24",
      "picture": "http://placehold.it/128x128",
      "age": 32,
      "accessLevel": "user",
      "firstName": "Logan",
      "lastName": "Garza",
      "company": "GRACKER",
      "email": "logan.garza@gracker.biz",
      "phone": "+7 (969) 414-3880",
      "address": "166 Green Street, Kirk, Nebraska, 4768",
      "about": "Eiusmod minim minim consequat officia magna mollit. Ea est non consequat aliquip ex sunt. Ex id veniam quis irure dolore culpa et consequat et sit ad adipisicing est. Incididunt eiusmod eiusmod est adipisicing. Deserunt dolore aliqua aute Lorem quis. Cupidatat id aliqua velit cillum mollit incididunt mollit. Consectetur consectetur adipisicing consequat do non magna culpa dolore laborum in.",
      "registered": "25.04.2018"
    },
    {
      "id": 3,
      "isActive": true,
      "balance": "$3,645.55",
      "picture": "http://placehold.it/128x128",
      "age": 23,
      "accessLevel": "guest",
      "firstName": "Shields",
      "lastName": "Weaver",
      "company": "TERRAGEN",
      "email": "shields.weaver@terragen.me",
      "phone": "+7 (919) 598-2827",
      "address": "220 Navy Street, Mapletown, Northern Mariana Islands, 2415",
      "about": "Ad cupidatat ad tempor ut et pariatur laboris consequat ipsum magna ut minim. Magna aliqua ipsum officia aliqua sunt eiusmod excepteur aute aute labore quis. Aute irure eiusmod Lorem exercitation nostrud nulla officia.",
      "registered": "24.10.2017"
    },
    {
      "id": 4,
      "isActive": false,
      "balance": "$1,804.78",
      "picture": "http://placehold.it/128x128",
      "age": 23,
      "accessLevel": "admin",
      "firstName": "Sandy",
      "lastName": "Young",
      "company": "ORBAXTER",
      "email": "sandy.young@orbaxter.tv",
      "phone": "+7 (874) 581-3038",
      "address": "139 Hastings Street, Springhill, Colorado, 2944",
      "about": "Anim ut aliqua fugiat excepteur culpa voluptate enim laborum laboris voluptate exercitation quis. Non tempor cupidatat aute pariatur. Enim mollit dolor nulla reprehenderit enim nisi est adipisicing excepteur tempor. Ut est eu reprehenderit et excepteur anim aute amet in eu. Amet amet dolore eu nulla ad. Veniam ad duis non est culpa tempor ex qui excepteur excepteur occaecat sunt sunt incididunt.",
      "registered": "20.02.2016"
    },
    {
      "id": 5,
      "isActive": false,
      "balance": "$2,554.45",
      "picture": "http://placehold.it/128x128",
      "age": 27,
      "accessLevel": "user",
      "firstName": "Miriam",
      "lastName": "Barlow",
      "company": "COMCUBINE",
      "email": "miriam.barlow@comcubine.name",
      "phone": "+7 (984) 536-3841",
      "address": "682 Beverly Road, Wilsonia, Wyoming, 557",
      "about": "Laboris laborum commodo quis eiusmod. Amet mollit aute excepteur officia officia quis commodo sint officia tempor quis. Sint aliquip elit aute incididunt enim cupidatat enim aute quis aliqua veniam. Amet ut ea magna tempor eiusmod ea ipsum ea culpa ad do anim tempor. Ea adipisicing minim magna pariatur dolor commodo ullamco labore ex voluptate magna ad. Ea dolor dolor ut sit est. Eiusmod reprehenderit non in aliqua irure culpa elit ad proident ut minim nulla.",
      "registered": "12.05.2016"
    },
    {
      "id": 6,
      "isActive": true,
      "balance": "$1,821.84",
      "picture": "http://placehold.it/128x128",
      "age": 29,
      "accessLevel": "user",
      "firstName": "Leann",
      "lastName": "Houston",
      "company": "KOZGENE",
      "email": "leann.houston@kozgene.com",
      "phone": "+7 (900) 415-3405",
      "address": "183 Emmons Avenue, Esmont, North Dakota, 6396",
      "about": "Sit do incididunt aliqua anim consequat commodo est proident nostrud nisi ullamco. Sit ipsum cillum labore velit non. Labore tempor aliqua ipsum elit. Ea commodo cillum pariatur fugiat eu.",
      "registered": "15.05.2015"
    },
    {
      "id": 7,
      "isActive": true,
      "balance": "$2,041.54",
      "picture": "http://placehold.it/128x128",
      "age": 34,
      "accessLevel": "admin",
      "firstName": "Chase",
      "lastName": "Wade",
      "company": "OVIUM",
      "email": "chase.wade@ovium.ca",
      "phone": "+7 (803) 545-3000",
      "address": "440 Lois Avenue, Marshall, Idaho, 177",
      "about": "Tempor sint culpa do do pariatur. Eu cupidatat esse irure aliqua ex est ad id nisi. Nulla sit irure anim minim do. Magna id commodo exercitation adipisicing officia labore voluptate quis consectetur ea commodo id.",
      "registered": "19.11.2018"
    },
    {
      "id": 8,
      "isActive": true,
      "balance": "$3,346.18",
      "picture": "http://placehold.it/128x128",
      "age": 36,
      "accessLevel": "admin",
      "firstName": "Shannon",
      "lastName": "Hooper",
      "company": "NETERIA",
      "email": "shannon.hooper@neteria.net",
      "phone": "+7 (869) 571-3501",
      "address": "194 Dictum Court, Sylvanite, Guam, 4109",
      "about": "Consectetur proident eu Lorem consequat proident laborum exercitation reprehenderit incididunt est enim nisi fugiat. Minim culpa aliquip occaecat et amet qui velit quis dolor eiusmod. Consectetur proident ex incididunt cillum mollit. Exercitation duis Lorem cillum excepteur commodo reprehenderit consectetur mollit in.",
      "registered": "19.03.2017"
    },
    {
      "id": 9,
      "isActive": false,
      "balance": "$3,000.7",
      "picture": "http://placehold.it/128x128",
      "age": "22",
      "accessLevel": "user",
      "firstName": "Case",
      "lastName": "Patton",
      "company": "QUIZKA",
      "email": "case.patton@quizka.io",
      "phone": "+7 (897) 570-2702",
      "address": "252 Madison Street, Brogan, Wisconsin, 9410",
      "about": "Voluptate tempor consequat duis reprehenderit adipisicing ea exercitation deserunt voluptate enim excepteur aute eiusmod. Occaecat tempor excepteur commodo ipsum dolor velit tempor dolore nulla laborum ea aliqua. Est cupidatat proident cupidatat cupidatat voluptate sit. Minim esse Lorem sit fugiat aliqua fugiat enim labore officia. Nisi culpa nostrud amet ea consequat ad dolor labore Lorem veniam enim. Pariatur do Lorem eiusmod amet laboris aliquip velit adipisicing reprehenderit voluptate adipisicing commodo ea.",
      "registered": "11.07.2016"
    },
    {
      "id": 10,
      "isActive": false,
      "balance": "$1,860.19",
      "picture": "http://placehold.it/128x128",
      "age": "23",
      "accessLevel": "admin",
      "firstName": "Charles",
      "lastName": "Calhoun",
      "company": "FLUM",
      "email": "charles.calhoun@flum.org",
      "phone": "+7 (843) 486-3765",
      "address": "732 Barwell Terrace, Deseret, Utah, 3494",
      "about": "Veniam ullamco ex reprehenderit ut excepteur labore nulla tempor ad ex. Anim enim nostrud eiusmod commodo sint. Lorem anim eiusmod laborum et deserunt esse aliqua irure eu proident proident mollit nulla laborum. Laborum excepteur est anim reprehenderit.",
      "registered": "03.11.2015"
    }
  ]
}